LICENSE
MANIFEST.in
NOTICE
README.rst
requirements.txt
setup.py
piwho/__init__.py
piwho/config.py
piwho/recognition.py
piwho/vad.py
piwho.egg-info/PKG-INFO
piwho.egg-info/SOURCES.txt
piwho.egg-info/dependency_links.txt
piwho.egg-info/not-zip-safe
piwho.egg-info/requires.txt
piwho.egg-info/top_level.txt
piwho/marf/Speaker.jar
piwho/marf/marf.jar