Metadata-Version: 1.1
Name: piwho
Version: 1.3.2
Summary: A python wrapper around MARF speaker recognition frameworkfor raspberry pi and other SBCs
Home-page: https://github.com/Adirockzz95/PiWho
Author: Aditya Khandkar
Author-email: khandkar.adi@gmail.com
License: MIT
Keywords: Speaker recognition Raspberry Pi MARF
Platform: UNKNOWN
Classifier: Development Status :: 5 - Production/Stable
Classifier: Intended Audience :: End Users/Desktop
Classifier: Intended Audience :: Developers
Classifier: Topic :: Multimedia :: Sound/Audio :: Speech
Classifier: Topic :: Multimedia :: Sound/Audio :: Analysis
Classifier: Topic :: Software Development :: Libraries :: Python Modules
Classifier: License :: OSI Approved :: MIT License
Classifier: Programming Language :: Python :: 2.7
Classifier: Programming Language :: Python :: 3.2
Classifier: Programming Language :: Python :: 3.3
Classifier: Programming Language :: Python :: 3.4
Classifier: Programming Language :: Python :: 3.5
Classifier: Programming Language :: Python :: 3.6
Classifier: Programming Language :: Python :: Implementation :: CPython
